wi_voice_main.py
wi_voice_main-0.1.0.dist-info/WHEEL
wi_voice_main-0.1.0.dist-info/METADATA
wi_voice_main-0.1.0.dist-info/RECORD
